cleantimer/__init__.py
cleantimer/cleantimer.py
cleantimer-0.0.2.dist-info/LICENSE
cleantimer-0.0.2.dist-info/METADATA
cleantimer-0.0.2.dist-info/WHEEL
cleantimer-0.0.2.dist-info/top_level.txt
cleantimer-0.0.2.dist-info/RECORD
