Metadata-Version: 2.1
Name: cleantimer
Version: 0.0.2
Summary: Track progress of long-running scripts, without cluttering your code with log statements.
Home-page: https://github.com/alecglen/cleantimer
Author: Alec Ostrander
License: GPLv3
Keywords: time,timer,progress
Classifier: Topic :: Utilities
Classifier: Intended Audience :: Developers
Classifier: Programming Language :: Python :: 3
Classifier: License :: OSI Approved :: GNU General Public License v3 (GPLv3)
Classifier: Operating System :: OS Independent
Requires-Python: >=3.6
License-File: LICENSE
Requires-Dist: contexttimer
Requires-Dist: tqdm
Requires-Dist: pandas
